aiida_porousmaterials/__init__.py
aiida_porousmaterials/calculations/__init__.py
aiida_porousmaterials/parser/__init__.py
aiida_porousmaterials/utils/__init__.py
aiida_porousmaterials/utils/base_parser.py
aiida_porousmaterials/utils/input_generator.py
aiida_porousmaterials-1.0.0a2.data/data/setup.json
aiida_porousmaterials-1.0.0a2.dist-info/LICENSE
aiida_porousmaterials-1.0.0a2.dist-info/METADATA
aiida_porousmaterials-1.0.0a2.dist-info/WHEEL
aiida_porousmaterials-1.0.0a2.dist-info/entry_points.txt
aiida_porousmaterials-1.0.0a2.dist-info/top_level.txt
aiida_porousmaterials-1.0.0a2.dist-info/RECORD
