Metadata-Version: 2.1
Name: aiida-porousmaterials
Version: 1.0.0a2
Summary: AiiDA plugin for PorousMaterials code
Home-page: https://github.com/pzarabadip/aiida-porousmaterials
Author: Pezhman Zarabadi-Poor
Author-email: pzarabadip@gmail.com
License: MIT
Platform: UNKNOWN
Classifier: Environment :: Plugins
Classifier: Programming Language :: Python :: 3.6
Classifier: Programming Language :: Python :: 3.7
Classifier: Programming Language :: Python :: 3.8
Classifier: Intended Audience :: Science/Research
Classifier: License :: OSI Approved :: MIT License
Classifier: Framework :: AiiDA
Requires-Dist: aiida-core[atomic_tools] (<2.0.0,>=1.0.0)
Requires-Dist: pandas
Provides-Extra: pre-commit
Requires-Dist: pre-commit (==1.18.3) ; extra == 'pre-commit'
Requires-Dist: yapf (==0.28.0) ; extra == 'pre-commit'
Requires-Dist: prospector (==1.1.7) ; extra == 'pre-commit'
Requires-Dist: pylint (==2.3.1) ; extra == 'pre-commit'
Provides-Extra: test
Requires-Dist: pgtest (==1.2.0) ; extra == 'test'
Requires-Dist: pytest (<5.0.0,>=4.4) ; extra == 'test'
Requires-Dist: pytest-cov (<3.0.0,>=2.6.1) ; extra == 'test'
